github_repo_deleter/repo_deleter.py
pygithubrepodeleter-1.0.0.dist-info/METADATA
pygithubrepodeleter-1.0.0.dist-info/WHEEL
pygithubrepodeleter-1.0.0.dist-info/entry_points.txt
pygithubrepodeleter-1.0.0.dist-info/top_level.txt
pygithubrepodeleter-1.0.0.dist-info/RECORD
