Metadata-Version: 2.1
Name: pygithubrepodeleter
Version: 1.0.0
Summary: This is just a very simple CLI to bulk delete github repositories
Home-page: UNKNOWN
Author: Xavier Tolza
Author-email: tolza.xavier@gmail.com
License: UNKNOWN
Platform: UNKNOWN
Requires-Dist: PyGithub
Requires-Dist: PyInquirer
